pyoptima/__init__.py
pyoptima/cli.py
pyoptima/config.py
pyoptima/exceptions.py
pyoptima/py.typed
pyoptima/api/__init__.py
pyoptima/api/main.py
pyoptima/api/utils.py
pyoptima/api/dependencies/__init__.py
pyoptima/api/dependencies/core.py
pyoptima/api/models/__init__.py
pyoptima/api/models/jobs.py
pyoptima/api/models/optimization.py
pyoptima/api/models/requests.py
pyoptima/api/models/responses.py
pyoptima/api/models/solvers.py
pyoptima/api/models/templates.py
pyoptima/api/routes/__init__.py
pyoptima/api/routes/v1/__init__.py
pyoptima/api/routes/v1/jobs.py
pyoptima/api/routes/v1/optimize.py
pyoptima/api/routes/v1/solvers.py
pyoptima/api/routes/v1/templates.py
pyoptima/api/services/__init__.py
pyoptima/api/services/job_manager.py
pyoptima/api/services/optimization_service.py
pyoptima/constraints/__init__.py
pyoptima/constraints/base.py
pyoptima/constraints/bounds.py
pyoptima/constraints/cardinality.py
pyoptima/constraints/linear.py
pyoptima/constraints/portfolio.py
pyoptima/constraints/risk.py
pyoptima/constraints/sector.py
pyoptima/constraints/turnover.py
pyoptima/core/__init__.py
pyoptima/core/problem.py
pyoptima/core/protocols.py
pyoptima/core/result.py
pyoptima/estimators/__init__.py
pyoptima/estimators/base.py
pyoptima/estimators/portfolio.py
pyoptima/etl/__init__.py
pyoptima/etl/adapter.py
pyoptima/etl/output.py
pyoptima/expression/__init__.py
pyoptima/expression/ast.py
pyoptima/expression/evaluator.py
pyoptima/expression/parser.py
pyoptima/io/__init__.py
pyoptima/io/data.py
pyoptima/io/readers.py
pyoptima/model/__init__.py
pyoptima/model/core.py
pyoptima/model/sets.py
pyoptima/objectives/__init__.py
pyoptima/objectives/base.py
pyoptima/objectives/portfolio.py
pyoptima/solvers/__init__.py
pyoptima/solvers/base.py
pyoptima/solvers/pyomo_solver.py
pyoptima/templates/__init__.py
pyoptima/templates/base.py
pyoptima/templates/classic.py
pyoptima/templates/facility.py
pyoptima/templates/mathematical.py
pyoptima/templates/network.py
pyoptima/templates/packing.py
pyoptima-0.0.5.dist-info/licenses/LICENSE
pyoptima-0.0.5.dist-info/METADATA
pyoptima-0.0.5.dist-info/WHEEL
pyoptima-0.0.5.dist-info/entry_points.txt
pyoptima-0.0.5.dist-info/top_level.txt
pyoptima-0.0.5.dist-info/RECORD
