Metadata-Version: 2.4
Name: pyoptima
Version: 0.0.5
Summary: Portfolio optimization with a sklearn-style API and config-driven workflows. Multiple objectives, constraints, and solvers.
Author-email: semantic developers <na@example.com>
License-Expression: MIT
Project-URL: Homepage, https://github.com/auscheng/pyoptima
Project-URL: Documentation, https://github.com/auscheng/pyoptima#readme
Project-URL: Repository, https://github.com/auscheng/pyoptima
Project-URL: Issues, https://github.com/auscheng/pyoptima/issues
Keywords: optimization,portfolio,mean-variance,sharpe,risk-parity,solver,pyomo
Classifier: Development Status :: 4 - Beta
Classifier: Intended Audience :: Developers
Classifier: Intended Audience :: Science/Research
Classifier: Programming Language :: Python :: 3
Classifier: Programming Language :: Python :: 3.10
Classifier: Programming Language :: Python :: 3.11
Classifier: Programming Language :: Python :: 3.12
Classifier: Topic :: Scientific/Engineering :: Mathematics
Requires-Python: >=3.10
License-File: LICENSE
Requires-Dist: pydantic>=2.0.0
Requires-Dist: pyomo>=6.0.0
Requires-Dist: numpy>=1.20.0
Requires-Dist: pandas>=1.3.0
Requires-Dist: pyyaml>=6.0.0
Requires-Dist: highspy>=1.0.0
Requires-Dist: cyipopt>=1.5.0
Provides-Extra: dev
Requires-Dist: pytest>=7.0.0; extra == "dev"
Requires-Dist: pytest-cov>=4.0.0; extra == "dev"
Requires-Dist: black>=23.0.0; extra == "dev"
Requires-Dist: isort>=5.12.0; extra == "dev"
Requires-Dist: mypy>=1.0.0; extra == "dev"
Requires-Dist: build>=0.10.0; extra == "dev"
Requires-Dist: twine>=4.0.0; extra == "dev"
Requires-Dist: jupyterlab>=4.0.0; extra == "dev"
Requires-Dist: ipykernel>=6.0.0; extra == "dev"
Requires-Dist: matplotlib>=3.5.0; extra == "dev"
Provides-Extra: api
Requires-Dist: fastapi>=0.104.0; extra == "api"
Requires-Dist: uvicorn[standard]>=0.24.0; extra == "api"
Requires-Dist: pydantic-settings>=2.0.0; extra == "api"
Requires-Dist: python-multipart>=0.0.6; extra == "api"
Provides-Extra: cli
Requires-Dist: rich>=13.0.0; extra == "cli"
Provides-Extra: ui
Requires-Dist: fastapi>=0.104.0; extra == "ui"
Requires-Dist: uvicorn[standard]>=0.24.0; extra == "ui"
Requires-Dist: httpx>=0.24.0; extra == "ui"
Requires-Dist: aiofiles>=23.0.0; extra == "ui"
Dynamic: license-file
